docs/00-getting_started.rst
docs/01-authentication.rst
docs/02-making-calls.rst
docs/03-examples.rst
docs/04-faq.rst
docs/90-api.rst
docs/Makefile
docs/conf.py
docs/index.rst
docs/make.bat
docs/_static/css/custom.css
docs/_static/images/mantelo-128.png
docs/_static/images/mantelo-256.png
docs/_static/images/mantelo-512.png
docs/_static/images/mantelo-social-preview.png
docs/_static/images/mantelo-text-900.png
docs/_static/images/mantelo.ico
docs/_static/images/mantelo.svg
docs/_templates/.gitkeep
docs/_templates/layout.html
mantelo/__init__.py
mantelo/client.py
mantelo/connection.py
mantelo/exceptions.py
mantelo/py.typed
mantelo/version.py
mantelo/internal/__init__.py
mantelo/internal/api.py
mantelo/internal/serializers.py
mantelo-2.2.0.dist-info/LICENSE
mantelo-2.2.0.dist-info/METADATA
mantelo-2.2.0.dist-info/WHEEL
mantelo-2.2.0.dist-info/top_level.txt
mantelo-2.2.0.dist-info/RECORD
