Metadata-Version: 2.1
Name: mantelo
Version: 2.2.0
Summary: ✨ Keycloak Admin REST Api Client for Python ✨
Author-email: Lucy Linder <lucy.derlin@gmail.com>
License:                                  Apache License
Project-URL: Homepage, https://github.com/derlin/mantelo
Project-URL: Documentation, https://mantelo.readthedocs.io/en/latest/
Project-URL: Source, https://github.com/derlin/mantelo
Project-URL: Issue tracker, https://github.com/derlin/mantelo/issues
Project-URL: Changelog, https://github.com/derlin/mantelo/CHANGELOG.md
Keywords: keycloak,http,rest,requests,client
Platform: any
Classifier: Intended Audience :: Developers
Classifier: Environment :: Web Environment
Classifier: License :: OSI Approved :: Apache Software License
Classifier: Operating System :: OS Independent
Classifier: Programming Language :: Python
Classifier: Programming Language :: Python :: 3.10
Classifier: Programming Language :: Python :: 3.11
Classifier: Programming Language :: Python :: 3.12
Classifier: Topic :: Internet :: WWW/HTTP
Classifier: Topic :: Software Development :: Libraries
Classifier: Topic :: Utilities
Requires-Python: >=3.10
License-File: LICENSE
Requires-Dist: attrs
Requires-Dist: requests
Provides-Extra: dev
Requires-Dist: build; extra == "dev"
Requires-Dist: coverage; extra == "dev"
Requires-Dist: tox; extra == "dev"
Requires-Dist: mypy; extra == "dev"
Requires-Dist: check-manifest; extra == "dev"
Requires-Dist: types-requests; extra == "dev"
Requires-Dist: types-slumber; extra == "dev"
Provides-Extra: test
Requires-Dist: pytest; extra == "test"
Requires-Dist: pytest-cov; extra == "test"
Provides-Extra: docs
Requires-Dist: sphinx; extra == "docs"
Requires-Dist: sphinx-book-theme; extra == "docs"
Requires-Dist: sphinx-autoapi; extra == "docs"
Requires-Dist: sphinx-copybutton; extra == "docs"
Requires-Dist: sphinxext-opengraph; extra == "docs"
